ROM/ROM.v
module ROM(input wire[11:0] A, output  wire[7:0] Y);
  assign Y = Memoria[A];
  reg[7:0] Memoria[0:4095];
  initial begin
    $readmemb("Memoria.list", Memoria);
  end
endmodule

ROM/ROM_tb.v
module testbenchROM();
reg[11:0] A;
wire[7:0] Y;

ROM RR(A, Y);

initial begin
#1
$display("ROM");
$display("A | Y");
$display("-----------|---------");
$monitor("%b |  %b", A, Y);
end
  initial begin
    A = 12'b000000000000;
  #1 A = 12'b000000000001;
  #1 A = 12'b000000000010;
  #1 A = 12'b000000000011;
  #1 A = 12'b000000000100;
  #1 A = 12'b000000000101;
  #1 A = 12'b000000000110;
  #1 A = 12'b000000000111;
  #1 A = 12'b000000001000;
  #1 A = 12'b000000001001;
  #1 A = 12'b000000001010;
  #1 A = 12'b000000001011;
  #1 A = 12'b000000001100;
  #1 A = 12'b000000001101;
  #1 A = 12'b000000001111;
  #1 A = 12'b000000010000;
  #1 A = 12'b000000010001;
  #1 A = 12'b000000010010;
  #1 A = 12'b000000010011;
  #1 A = 12'b000000010100;
  #1 A = 12'b000000010101;
  #1 A = 12'b000000010110;
  #1 A = 12'b000000010111;
  #1 A = 12'b000000011000;





  end

 initial
   #500 $finish;
 initial begin
     $dumpfile("ROM_tb.vcd");
     $dumpvars(0, testbenchROM);
   end
 endmodule

ROM/ROM_tb.vcd
$date
	Sat Oct 24 21:35:15 2020
$end
$version
	Icarus Verilog
$end
$timescale
	1ps
$end
$scope module testbenchROM $end
$var wire 8 ! Y [7:0] $end
$var reg 12 " A [11:0] $end
$scope module RR $end
$var wire 12 # A [11:0] $end
$var wire 8 $ Y [7:0] $end
$upscope $end
$upscope $end
$enddefinitions $end
#0
$dumpvars
b0 $
b0 #
b0 "
b0 !
$end
#1
b1 !
b1 $
b1 "
b1 #
#2
b10 !
b10 $
b10 "
b10 #
#3
b11 !
b11 $
b11 "
b11 #
#4
b100 !
b100 $
b100 "
b100 #
#5
b101 !
b101 $
b101 "
b101 #
#6
b111 !
b111 $
b110 "
b110 #
#7
b1000 !
b1000 $
b111 "
b111 #
#8
b1001 !
b1001 $
b1000 "
b1000 #
#9
b1010 !
b1010 $
b1001 "
b1001 #
#10
b1011 !
b1011 $
b1010 "
b1010 #
#11
b1100 !
b1100 $
b1011 "
b1011 #
#12
b1101 !
b1101 $
b1100 "
b1100 #
#13
b1110 !
b1110 $
b1101 "
b1101 #
#14
b10000 !
b10000 $
b1111 "
b1111 #
#15
b10001 !
b10001 $
b10000 "
b10000 #
#16
b10010 !
b10010 $
b10001 "
b10001 #
#17
b10011 !
b10011 $
b10010 "
b10010 #
#18
b10100 !
b10100 $
b10011 "
b10011 #
#19
b10101 !
b10101 $
b10100 "
b10100 #
#20
b10110 !
b10110 $
b10101 "
b10101 #
#21
b10111 !
b10111 $
b10110 "
b10110 #
#22
b11000 !
b11000 $
b10111 "
b10111 #
#23
b11001 !
b11001 $
b11000 "
b11000 #
