ALU/ALU.v
module ALU(input wire [3:0] A, input wire [3:0] B, input wire [2:0] R, output reg [3:0] Y);
  always @ ( * ) begin
  case(R)
      3'b000: Y = A & B;
      3'b001: Y = A | B;
      3'b010: Y = A + B;
      default: Y = A & B;
      3'b100: Y = A & ~B;
      3'b101: Y = A | ~B;
      3'b110: Y = A - B;
      3'b111: Y = (A > B)?3'b001 :3'b000;
  endcase
  end
endmodule

ALU/ALU_tb.v
module testbenchALU();
reg[3:0] A;
reg[3:0] B;
reg[2:0] R;
wire[3:0] Y;

ALU AA(A, B, R, Y);

initial begin
#1
$display(" ALU");
$display("A B R | Y");
$display("-----------|---------");
$monitor("%b %b %b |  %b", A, B, R, Y);
end
  initial begin
    A = 4'b0000; B = 4'b0000; R = 4'b000;
  #1 A = 4'b0100; B = 4'b1000; R = 4'b000;
  #1 A = 4'b0100; B = 4'b1000; R = 4'b001;
  #1 A = 4'b0010; B = 4'b0001; R = 4'b010;
  #1 A = 4'b0010; B = 4'b0001; R = 4'b100;
  #1 A = 4'b0011; B = 4'b0110; R = 4'b101;
  #1 A = 4'b0011; B = 4'b0110; R = 4'b110;
  #1 A = 4'b0011; B = 4'b0110; R = 4'b111;




  end

 initial
   #500 $finish;
 initial begin
     $dumpfile("ALU_tb.vcd");
     $dumpvars(0, testbenchALU);
   end
 endmodule

ALU/ALU_tb.vcd
$date
	Sat Oct 24 20:44:16 2020
$end
$version
	Icarus Verilog
$end
$timescale
	1ps
$end
$scope module testbenchALU $end
$var wire 4 ! Y [3:0] $end
$var reg 4 " A [3:0] $end
$var reg 4 # B [3:0] $end
$var reg 3 $ R [2:0] $end
$scope module AA $end
$var wire 4 % A [3:0] $end
$var wire 4 & B [3:0] $end
$var wire 3 ' R [2:0] $end
$var reg 4 ( Y [3:0] $end
$upscope $end
$upscope $end
$enddefinitions $end
#0
$dumpvars
b0 (
b0 '
b0 &
b0 %
b0 $
b0 #
b0 "
b0 !
$end
#1
b1000 #
b1000 &
b100 "
b100 %
#2
b1100 !
b1100 (
b1 $
b1 '
#3
b11 !
b11 (
b10 $
b10 '
b1 #
b1 &
b10 "
b10 %
#4
b10 !
b10 (
b100 $
b100 '
#5
b1011 !
b1011 (
b101 $
b101 '
b110 #
b110 &
b11 "
b11 %
#6
b1101 !
b1101 (
b110 $
b110 '
#7
b0 !
b0 (
b111 $
b111 '
