CONTADOR/lab7.v


module contador(input wire clk, reset, enable, loadbit, input wire[11:0] load ,output reg [11:0]cont);
  always @ (posedge clk or posedge reset or posedge loadbit) begin
  if (reset)
    cont <= 12'b000000000000;
  else if (loadbit)
      cont <= load;
  else if (enable)
      cont <= cont + 12'b1;
  end
endmodule

CONTADOR/lab_tb.v
module testbench();

reg clk, reset, enable, loadbit;
reg[11:0] load;
wire[11:0] cont;
contador U1(clk, reset, enable, loadbit, load, cont);

always
  #1 clk <= ~clk;

initial begin
#1
$display("Contador");
$display("clk reset enable loadbit load| cont");
$display("-----------|---------");
$monitor("%b %b %b %b %b |  %b", clk, reset, enable, loadbit, load, cont);
end
  initial begin
    clk = 0; reset = 0; enable = 0; loadbit = 0; load = 12'b000000000000;
  #1 reset = 0;
  #1 reset = 0;
  #1 reset = 0;
  #1 reset = 0;
  #1 reset = 1;
  #1 reset = 0;
  #1 loadbit = 1; load = 12'b000100000000;
  #1 loadbit = 1;
  #1 loadbit = 1;
  #1 loadbit = 1; enable = 1;
  #1 loadbit = 0;



  end

 initial
   #500 $finish;
 initial begin
     $dumpfile("lab_tb.vcd");
     $dumpvars(0, testbench);
   end
 endmodule

CONTADOR/lab_tb.vcd
$date
	Sat Oct 24 21:28:21 2020
$end
$version
	Icarus Verilog
$end
$timescale
	1ps
$end
$scope module testbench $end
$var wire 12 ! cont [11:0] $end
$var reg 1 " clk $end
$var reg 1 # enable $end
$var reg 12 $ load [11:0] $end
$var reg 1 % loadbit $end
$var reg 1 & reset $end
$scope module U1 $end
$var wire 1 " clk $end
$var wire 1 # enable $end
$var wire 12 ' load [11:0] $end
$var wire 1 % loadbit $end
$var wire 1 & reset $end
$var reg 12 ( cont [11:0] $end
$upscope $end
$upscope $end
$enddefinitions $end
#0
$dumpvars
bx (
b0 '
0&
0%
b0 $
0#
0"
bx !
$end
#1
1"
#2
0"
#3
1"
#4
0"
#5
b0 !
b0 (
1"
1&
#6
0"
0&
#7
b100000000 !
b100000000 (
1"
b100000000 $
b100000000 '
1%
#8
0"
#9
1"
#10
0"
1#
#11
b100000001 !
b100000001 (
1"
0%
#12
0"
#13
b100000010 !
b100000010 (
1"
#14
0"
#15
b100000011 !
b100000011 (
1"
#16
0"
#17
b100000100 !
b100000100 (
1"
#18
0"
#19
b100000101 !
b100000101 (
1"
#20
0"
#21
b100000110 !
b100000110 (
1"
#22
0"
#23
b100000111 !
b100000111 (
1"
#24
0"
#25
b100001000 !
b100001000 (
1"
#26
0"
#27
b100001001 !
b100001001 (
1"
#28
0"
#29
b100001010 !
b100001010 (
1"
#30
0"
#31
b100001011 !
b100001011 (
1"
#32
0"
#33
b100001100 !
b100001100 (
1"
#34
0"
#35
b100001101 !
b100001101 (
1"
#36
0"
#37
b100001110 !
b100001110 (
1"
#38
0"
#39
b100001111 !
b100001111 (
1"
#40
0"
#41
b100010000 !
b100010000 (
1"
#42
0"
#43
b100010001 !
b100010001 (
1"
#44
0"
#45
b100010010 !
b100010010 (
1"
#46
0"
#47
b100010011 !
b100010011 (
1"
#48
0"
#49
b100010100 !
b100010100 (
1"
#50
0"
#51
b100010101 !
b100010101 (
1"
#52
0"
#53
b100010110 !
b100010110 (
1"
#54
0"
#55
b100010111 !
b100010111 (
1"
#56
0"
#57
b100011000 !
b100011000 (
1"
#58
0"
#59
b100011001 !
b100011001 (
1"
#60
0"
#61
b100011010 !
b100011010 (
1"
#62
0"
#63
b100011011 !
b100011011 (
1"
#64
0"
#65
b100011100 !
b100011100 (
1"
#66
0"
#67
b100011101 !
b100011101 (
1"
#68
0"
#69
b100011110 !
b100011110 (
1"
#70
0"
#71
b100011111 !
b100011111 (
1"
#72
0"
#73
b100100000 !
b100100000 (
1"
#74
0"
#75
b100100001 !
b100100001 (
1"
#76
0"
#77
b100100010 !
b100100010 (
1"
#78
0"
#79
b100100011 !
b100100011 (
1"
#80
0"
#81
b100100100 !
b100100100 (
1"
#82
0"
#83
b100100101 !
b100100101 (
1"
#84
0"
#85
b100100110 !
b100100110 (
1"
#86
0"
#87
b100100111 !
b100100111 (
1"
#88
0"
#89
b100101000 !
b100101000 (
1"
#90
0"
#91
b100101001 !
b100101001 (
1"
#92
0"
#93
b100101010 !
b100101010 (
1"
#94
0"
#95
b100101011 !
b100101011 (
1"
#96
0"
#97
b100101100 !
b100101100 (
1"
#98
0"
#99
b100101101 !
b100101101 (
1"
#100
0"
#101
b100101110 !
b100101110 (
1"
#102
0"
#103
b100101111 !
b100101111 (
1"
#104
0"
#105
b100110000 !
b100110000 (
1"
#106
0"
#107
b100110001 !
b100110001 (
1"
#108
0"
#109
b100110010 !
b100110010 (
1"
#110
0"
#111
b100110011 !
b100110011 (
1"
#112
0"
#113
b100110100 !
b100110100 (
1"
#114
0"
#115
b100110101 !
b100110101 (
1"
#116
0"
#117
b100110110 !
b100110110 (
1"
#118
0"
#119
b100110111 !
b100110111 (
1"
#120
0"
#121
b100111000 !
b100111000 (
1"
#122
0"
#123
b100111001 !
b100111001 (
1"
#124
0"
#125
b100111010 !
b100111010 (
1"
#126
0"
#127
b100111011 !
b100111011 (
1"
#128
0"
#129
b100111100 !
b100111100 (
1"
#130
0"
#131
b100111101 !
b100111101 (
1"
#132
0"
#133
b100111110 !
b100111110 (
1"
#134
0"
#135
b100111111 !
b100111111 (
1"
#136
0"
#137
b101000000 !
b101000000 (
1"
#138
0"
#139
b101000001 !
b101000001 (
1"
#140
0"
#141
b101000010 !
b101000010 (
1"
#142
0"
#143
b101000011 !
b101000011 (
1"
#144
0"
#145
b101000100 !
b101000100 (
1"
#146
0"
#147
b101000101 !
b101000101 (
1"
#148
0"
#149
b101000110 !
b101000110 (
1"
#150
0"
#151
b101000111 !
b101000111 (
1"
#152
0"
#153
b101001000 !
b101001000 (
1"
#154
0"
#155
b101001001 !
b101001001 (
1"
#156
0"
#157
b101001010 !
b101001010 (
1"
#158
0"
#159
b101001011 !
b101001011 (
1"
#160
0"
#161
b101001100 !
b101001100 (
1"
#162
0"
#163
b101001101 !
b101001101 (
1"
#164
0"
#165
b101001110 !
b101001110 (
1"
#166
0"
#167
b101001111 !
b101001111 (
1"
#168
0"
#169
b101010000 !
b101010000 (
1"
#170
0"
#171
b101010001 !
b101010001 (
1"
#172
0"
#173
b101010010 !
b101010010 (
1"
#174
0"
#175
b101010011 !
b101010011 (
1"
#176
0"
#177
b101010100 !
b101010100 (
1"
#178
0"
#179
b101010101 !
b101010101 (
1"
#180
0"
#181
b101010110 !
b101010110 (
1"
#182
0"
#183
b101010111 !
b101010111 (
1"
#184
0"
#185
b101011000 !
b101011000 (
1"
#186
0"
#187
b101011001 !
b101011001 (
1"
#188
0"
#189
b101011010 !
b101011010 (
1"
#190
0"
#191
b101011011 !
b101011011 (
1"
#192
0"
#193
b101011100 !
b101011100 (
1"
#194
0"
#195
b101011101 !
b101011101 (
1"
#196
0"
#197
b101011110 !
b101011110 (
1"
#198
0"
#199
b101011111 !
b101011111 (
1"
#200
0"
#201
b101100000 !
b101100000 (
1"
#202
0"
#203
b101100001 !
b101100001 (
1"
#204
0"
#205
b101100010 !
b101100010 (
1"
#206
0"
#207
b101100011 !
b101100011 (
1"
#208
0"
#209
b101100100 !
b101100100 (
1"
#210
0"
#211
b101100101 !
b101100101 (
1"
#212
0"
#213
b101100110 !
b101100110 (
1"
#214
0"
#215
b101100111 !
b101100111 (
1"
#216
0"
#217
b101101000 !
b101101000 (
1"
#218
0"
#219
b101101001 !
b101101001 (
1"
#220
0"
#221
b101101010 !
b101101010 (
1"
#222
0"
#223
b101101011 !
b101101011 (
1"
#224
0"
#225
b101101100 !
b101101100 (
1"
#226
0"
#227
b101101101 !
b101101101 (
1"
#228
0"
#229
b101101110 !
b101101110 (
1"
#230
0"
#231
b101101111 !
b101101111 (
1"
#232
0"
#233
b101110000 !
b101110000 (
1"
#234
0"
#235
b101110001 !
b101110001 (
1"
#236
0"
#237
b101110010 !
b101110010 (
1"
#238
0"
#239
b101110011 !
b101110011 (
1"
#240
0"
#241
b101110100 !
b101110100 (
1"
#242
0"
#243
b101110101 !
b101110101 (
1"
#244
0"
#245
b101110110 !
b101110110 (
1"
#246
0"
#247
b101110111 !
b101110111 (
1"
#248
0"
#249
b101111000 !
b101111000 (
1"
#250
0"
#251
b101111001 !
b101111001 (
1"
#252
0"
#253
b101111010 !
b101111010 (
1"
#254
0"
#255
b101111011 !
b101111011 (
1"
#256
0"
#257
b101111100 !
b101111100 (
1"
#258
0"
#259
b101111101 !
b101111101 (
1"
#260
0"
#261
b101111110 !
b101111110 (
1"
#262
0"
#263
b101111111 !
b101111111 (
1"
#264
0"
#265
b110000000 !
b110000000 (
1"
#266
0"
#267
b110000001 !
b110000001 (
1"
#268
0"
#269
b110000010 !
b110000010 (
1"
#270
0"
#271
b110000011 !
b110000011 (
1"
#272
0"
#273
b110000100 !
b110000100 (
1"
#274
0"
#275
b110000101 !
b110000101 (
1"
#276
0"
#277
b110000110 !
b110000110 (
1"
#278
0"
#279
b110000111 !
b110000111 (
1"
#280
0"
#281
b110001000 !
b110001000 (
1"
#282
0"
#283
b110001001 !
b110001001 (
1"
#284
0"
#285
b110001010 !
b110001010 (
1"
#286
0"
#287
b110001011 !
b110001011 (
1"
#288
0"
#289
b110001100 !
b110001100 (
1"
#290
0"
#291
b110001101 !
b110001101 (
1"
#292
0"
#293
b110001110 !
b110001110 (
1"
#294
0"
#295
b110001111 !
b110001111 (
1"
#296
0"
#297
b110010000 !
b110010000 (
1"
#298
0"
#299
b110010001 !
b110010001 (
1"
#300
0"
#301
b110010010 !
b110010010 (
1"
#302
0"
#303
b110010011 !
b110010011 (
1"
#304
0"
#305
b110010100 !
b110010100 (
1"
#306
0"
#307
b110010101 !
b110010101 (
1"
#308
0"
#309
b110010110 !
b110010110 (
1"
#310
0"
#311
b110010111 !
b110010111 (
1"
#312
0"
#313
b110011000 !
b110011000 (
1"
#314
0"
#315
b110011001 !
b110011001 (
1"
#316
0"
#317
b110011010 !
b110011010 (
1"
#318
0"
#319
b110011011 !
b110011011 (
1"
#320
0"
#321
b110011100 !
b110011100 (
1"
#322
0"
#323
b110011101 !
b110011101 (
1"
#324
0"
#325
b110011110 !
b110011110 (
1"
#326
0"
#327
b110011111 !
b110011111 (
1"
#328
0"
#329
b110100000 !
b110100000 (
1"
#330
0"
#331
b110100001 !
b110100001 (
1"
#332
0"
#333
b110100010 !
b110100010 (
1"
#334
0"
#335
b110100011 !
b110100011 (
1"
#336
0"
#337
b110100100 !
b110100100 (
1"
#338
0"
#339
b110100101 !
b110100101 (
1"
#340
0"
#341
b110100110 !
b110100110 (
1"
#342
0"
#343
b110100111 !
b110100111 (
1"
#344
0"
#345
b110101000 !
b110101000 (
1"
#346
0"
#347
b110101001 !
b110101001 (
1"
#348
0"
#349
b110101010 !
b110101010 (
1"
#350
0"
#351
b110101011 !
b110101011 (
1"
#352
0"
#353
b110101100 !
b110101100 (
1"
#354
0"
#355
b110101101 !
b110101101 (
1"
#356
0"
#357
b110101110 !
b110101110 (
1"
#358
0"
#359
b110101111 !
b110101111 (
1"
#360
0"
#361
b110110000 !
b110110000 (
1"
#362
0"
#363
b110110001 !
b110110001 (
1"
#364
0"
#365
b110110010 !
b110110010 (
1"
#366
0"
#367
b110110011 !
b110110011 (
1"
#368
0"
#369
b110110100 !
b110110100 (
1"
#370
0"
#371
b110110101 !
b110110101 (
1"
#372
0"
#373
b110110110 !
b110110110 (
1"
#374
0"
#375
b110110111 !
b110110111 (
1"
#376
0"
#377
b110111000 !
b110111000 (
1"
#378
0"
#379
b110111001 !
b110111001 (
1"
#380
0"
#381
b110111010 !
b110111010 (
1"
#382
0"
#383
b110111011 !
b110111011 (
1"
#384
0"
#385
b110111100 !
b110111100 (
1"
#386
0"
#387
b110111101 !
b110111101 (
1"
#388
0"
#389
b110111110 !
b110111110 (
1"
#390
0"
#391
b110111111 !
b110111111 (
1"
#392
0"
#393
b111000000 !
b111000000 (
1"
#394
0"
#395
b111000001 !
b111000001 (
1"
#396
0"
#397
b111000010 !
b111000010 (
1"
#398
0"
#399
b111000011 !
b111000011 (
1"
#400
0"
#401
b111000100 !
b111000100 (
1"
#402
0"
#403
b111000101 !
b111000101 (
1"
#404
0"
#405
b111000110 !
b111000110 (
1"
#406
0"
#407
b111000111 !
b111000111 (
1"
#408
0"
#409
b111001000 !
b111001000 (
1"
#410
0"
#411
b111001001 !
b111001001 (
1"
#412
0"
#413
b111001010 !
b111001010 (
1"
#414
0"
#415
b111001011 !
b111001011 (
1"
#416
0"
#417
b111001100 !
b111001100 (
1"
#418
0"
#419
b111001101 !
b111001101 (
1"
#420
0"
#421
b111001110 !
b111001110 (
1"
#422
0"
#423
b111001111 !
b111001111 (
1"
#424
0"
#425
b111010000 !
b111010000 (
1"
#426
0"
#427
b111010001 !
b111010001 (
1"
#428
0"
#429
b111010010 !
b111010010 (
1"
#430
0"
#431
b111010011 !
b111010011 (
1"
#432
0"
#433
b111010100 !
b111010100 (
1"
#434
0"
#435
b111010101 !
b111010101 (
1"
#436
0"
#437
b111010110 !
b111010110 (
1"
#438
0"
#439
b111010111 !
b111010111 (
1"
#440
0"
#441
b111011000 !
b111011000 (
1"
#442
0"
#443
b111011001 !
b111011001 (
1"
#444
0"
#445
b111011010 !
b111011010 (
1"
#446
0"
#447
b111011011 !
b111011011 (
1"
#448
0"
#449
b111011100 !
b111011100 (
1"
#450
0"
#451
b111011101 !
b111011101 (
1"
#452
0"
#453
b111011110 !
b111011110 (
1"
#454
0"
#455
b111011111 !
b111011111 (
1"
#456
0"
#457
b111100000 !
b111100000 (
1"
#458
0"
#459
b111100001 !
b111100001 (
1"
#460
0"
#461
b111100010 !
b111100010 (
1"
#462
0"
#463
b111100011 !
b111100011 (
1"
#464
0"
#465
b111100100 !
b111100100 (
1"
#466
0"
#467
b111100101 !
b111100101 (
1"
#468
0"
#469
b111100110 !
b111100110 (
1"
#470
0"
#471
b111100111 !
b111100111 (
1"
#472
0"
#473
b111101000 !
b111101000 (
1"
#474
0"
#475
b111101001 !
b111101001 (
1"
#476
0"
#477
b111101010 !
b111101010 (
1"
#478
0"
#479
b111101011 !
b111101011 (
1"
#480
0"
#481
b111101100 !
b111101100 (
1"
#482
0"
#483
b111101101 !
b111101101 (
1"
#484
0"
#485
b111101110 !
b111101110 (
1"
#486
0"
#487
b111101111 !
b111101111 (
1"
#488
0"
#489
b111110000 !
b111110000 (
1"
#490
0"
#491
b111110001 !
b111110001 (
1"
#492
0"
#493
b111110010 !
b111110010 (
1"
#494
0"
#495
b111110011 !
b111110011 (
1"
#496
0"
#497
b111110100 !
b111110100 (
1"
#498
0"
#499
b111110101 !
b111110101 (
1"
